emanim/__init__.py
emanim/emobjects.py
emanim/escene.py
emanim-0.3.2.dist-info/LICENSE
emanim-0.3.2.dist-info/METADATA
emanim-0.3.2.dist-info/WHEEL
emanim-0.3.2.dist-info/top_level.txt
emanim-0.3.2.dist-info/RECORD
