Metadata-Version: 2.1
Name: emanim
Version: 0.3.2
Summary: Python module for subtitles in manim
Author-email: MrShprotter <lazey07@proton.me>
License: GNU GENERAL PUBLIC LICENSE
Project-URL: Homepage, https://github.com/MrShprotter/emanim
Project-URL: Bug Tracker, https://github.com/MrShprotter/emanim/issues
Keywords: python,python3,manim
Classifier: License :: OSI Approved :: GNU General Public License v3 or later (GPLv3+)
Classifier: Operating System :: OS Independent
Classifier: Programming Language :: Python :: 3
License-File: LICENSE
